requests_html_macro.py
requests_html_macros-0.1.1.dist-info/DESCRIPTION.rst
requests_html_macros-0.1.1.dist-info/METADATA
requests_html_macros-0.1.1.dist-info/RECORD
requests_html_macros-0.1.1.dist-info/WHEEL
requests_html_macros-0.1.1.dist-info/metadata.json
requests_html_macros-0.1.1.dist-info/top_level.txt
