Metadata-Version: 2.0
Name: requests-html-macros
Version: 0.1.1
Summary: HTML Parsing Macro things for Humans.
Home-page: https://github.com/erinxocon/requests-html-macros
Author: Erin O'Connell
Author-email: erinocon5@gmail.com
License: MIT
Platform: UNKNOWN
Classifier: License :: OSI Approved :: MIT License
Classifier: Programming Language :: Python
Classifier: Programming Language :: Python :: 3.6
Classifier: Programming Language :: Python :: Implementation :: CPython
Requires-Python: >=3.6.0
Requires-Dist: requests-html
